{
    "117": {
        "Tag": "fashion",
        "Id": "20221127A05DXZ_125",
        "Url": "https://new.qq.com/omn/20221127/20221127A05DXZ00.html",
        "Title": "周数据｜欧莱雅推出新品牌/锦波生物重启IPO",
        "Author": "海报时尚网",
        "Publish_Date": "2022-11-27",
        "Post_time": "18:11",
        "Content": "\n  - 为你摘取每周最重要的行业数据要闻 \n品牌\n2倍\n联合利华旗下THE LAUNDRESS产品存在潜在微生物污染风险\n日前，联合利华旗下高端洗护品牌THE LAUNDRESS发布安全隐患通知，称部分产品存在潜在微生物污染风险，建议停止使用现有的THE LAUNDRESS产品。同时，官方旗舰店发布产品召回公告，将召回部分THE LAUNDRESS牌洗衣液、柔顺剂和家庭清洁用品，补偿方案为换货可获得2倍积分，可兑换同规格产品两瓶，或按照实付金额退款。\n目前，店铺内的洗衣液商品均已下架，只剩下香氛、去渍皂、除皱喷雾等少量商品。 \n2022年\n伊蒂之屋天猫旗舰店暂停运营\n近日，爱茉莉太平洋集团旗下的伊蒂之屋天猫旗舰店宣布暂停运营，恢复时间待定。据悉，2020年中旬，伊蒂之屋陆续关闭中国内地所有线下门店，官方小程序商城也于2022年初闭店。爱茉莉太平洋集团相关负责人表示，只是一个短期调整，明年一季度会重新开业。\n目前，伊蒂之屋在京东的官方旗舰店以及天猫海外旗舰店正常运营。 \n第三方\n欧莱雅通过合资方式推出新品牌 Shihyo\n近日，欧莱雅集团宣布与韩国新罗酒店Hotel Shilla和免税店运营商Anchor Equity Partners合作，通过第三方合资企业Loshian推出了一个名为 Shihyo 的高端美容品牌，这是欧莱雅首次通过合资方式推出新的美妆品牌。据介绍，Shihyo以“24节气”为灵感，将推出24种不同草本成分的安瓶，此外，还有洗面奶、精华液、面霜、洗发水及护发素等护理产品系列。\n对此，不少网友认为“二十四节气”是中国特有的时间知识体系，对韩国公司以‘亚洲二十四节气’为灵感的说法表示不满。11月25日，欧莱雅中国发布声明，称对韩国合资公司新品牌发布的新闻稿没有准确表述二十四节起源于中国表示歉意，并表示始终认为二十四节气是源于中国的宝贵文化遗产。\n1000万元\n路威酩轩诉欧莱雅侵害商标权案中止审理\n近日，LVMH集团关联公司路威酩轩香水化妆品(上海)有限公司与欧莱雅(中国)有限公司侵害商标权纠纷、不正当竞争纠纷一审裁定书公开。文书显示，路威酩轩公司诉称，欧莱雅公司于2019年模仿法国娇兰于2010年推出的名为“ABEILLEROYALE 帝皇蜂姿”的护肤产品，涉嫌商标侵权、不正当竞争等，并向欧莱雅公司索赔1000万元。\n据悉，被告欧莱雅公司在提交答辩状期间对管辖权提出异议，于去年五月被驳回。日前，因新冠疫情影响，相关诉讼活动在较长期间内不能正常运行，本案中止诉讼。\n20个\n法国欧珑将专注亚太市场\n日前，欧莱雅集团旗下香氛品牌欧珑Atelier Cologne发布全新品牌重塑战略计划，将在中短期内专注亚太市场。据悉，Atelier Cologne于2022年初宣布退出北美市场，在欧洲市场也没有任何实体店，电商店也不再向该地区发货，该品牌在全球拥有20个销售点，今年还在广州开了一家新店。\n欧珑Atelier Cologne创立于2009年，于2016年被欧莱雅集团收购。该品牌营销总监表示：近年来，欧珑在亚洲有了明显发展，特别是在中国，我们也入驻了天猫，预计到2025年，中国将成为世界第二大高级香水市场。\nIPO\n7.65亿\n染发剂原料“第一股”来了？\n近日，浙江鼎龙科技股份有限公司再次更新招股说明书，拟在上海证券交易所上市。公司首次公开拟发行不超过5888万股，占发行后总股本的比例不低于25%，本次拟投入募资7.65亿元。据悉，今年6月递交招股书后，证监会对鼎龙科技给出了四大类别总计44条反馈意见，提到了历次股权转让与增资、关联交易等相关问题。有投资人表示，其募资合理性存疑。\n信息显示，鼎龙科技产品主要为染发剂原料、植保材料、特种工程材料单体等精细化工产品，与欧莱雅、汉高、科蒂等建立了深度合作关系。根据招股书，如若鼎龙科技能够成功于沪市主板上市，便有望成为染发剂原料“第一股”。\n2.51亿元\n锦波生物重启北交所IPO\n11月23日 ，锦波生物发布公告称，已经向北交所提交了恢复审核的申请及相关资料，目前已恢复审核 。2021年12月， 锦波生物冲击北交所，2022年9月，锦波生物因需要更新招股书引用的财务资料，中止北交所上市审核。报告显示，2022年前三季度，锦波生物实现营收2.51亿元，同比增长70.27%，净利润7023.78万元，同比增长97.78%。\n公开资料显示，锦波生物成立于2008年，主营业务为以重组胶原蛋白产品和抗HPV生物蛋白产品为核心的各类医疗器械、功能性护肤品的研发、生产及销售。\n \n财报\n1亿元\n逸仙电商第三季度卖了8.58亿\n11月22晚，逸仙电商发布截至9月30日的2022年第三季度财报。财报显示，逸仙电商第三季度总净营收为8.58亿元，其中护肤业务营收2.694亿元，同比增长33%；净亏损为2.107亿元，同比收窄41.7%；毛利率从去年同期的67.9%上升至68.9%。截至三季度末，逸仙电商2022年研发投入累计已超过1亿元。\n结合逸仙电商2022年Q1、Q2表现，前三季度，逸仙电商营收共超27亿元，护肤品牌已成为稳定的业绩增长引擎。总体来看，逸仙电商已从快战略转向稳经营，从单一依赖彩妆到依靠“护肤+彩妆”两条腿走路。\n市场\n60万+\n谁会是中国“小棕瓶”？\n化妆品观察围绕上市时间超过2年、单店月销量10万+、具备核心成分和科技、细分赛道表现突出等多个维度，总结梳理了天猫国货美妆大单品表单。本次统计的13个品牌中，天猫月销量10万+的单品共有24个，其中有12个单品月销量在20万+——40万+，更有2个超级单品月销量达到60万+。\n据统计，大单品大多数为品牌贡献了较大份额的销售；产品模型多为高附加值单品+独家品牌符号；营销方面主打代言人+达人，让种草养草转化“一条龙”。\n监管 \n45批次\n国家药监局又通报一批不合规化妆品\n11月22日，国家药监局发布关于45批次不符合规定化妆品的通告。通告显示，经海南省药品检验所等单位检验，产品标签标示为广州赛丝化妆品有限公司生产的赛丝之秀润黑露(自然黑)等45批次化妆品不符合规定，被通报产品包括染发膏 、隔离乳等。其中， “欧莱雅新多重防护隔离露”检出产品标签中未标识的防晒剂。\n11月23日，欧莱雅（中国）有限公司发布声明表示，经监管部门共同协查鉴定复核，被抽查出不合格的欧莱雅新多重防护隔离露确认为假冒产品。\n200万元\n一网店伪造化妆品授权书被罚\n近日，湖南高院官方微信公众号公布了一则典型案例，杨某以低价进购菲洛嘉、德玛贝尔等品牌假冒伪劣产品在淘宝网店中售卖，并采取P授权书，对部分产品贴防伪标签再销售，利用虚假身份通过物流以逃避查处等手段非法获利。杨某因销售假冒注册商标的商品罪等被处罚金二百万元及有期徒刑九年。\n销售假冒注册商标的商品，是一种在剽窃注册人商品信誉的同时还严重损害消费者权益的违法行为，侵犯的是国家对商标的管理制度和他人注册商标的专用权。\n33箱\n两千余瓶假冒希思黎被查获\n据报道，南庄市场监督管理所收到希思黎（上海）化妆品商贸有限公司的授权委托方的投诉，反映南庄镇东村某仓库里面存放有侵犯希思黎（上海）化妆品商贸有限公司注册商标“sisley”的化妆品。11月18日，执法人员在现场核查发现33箱共计两千余瓶“sisley”乳液，经鉴定，该批乳液是侵犯“sisley”注册商标专用权的商品。\n该批化妆品属于涉嫌侵犯他人注册商标专用权的物品， 执法人员现场检查时无人认领该批“sisley”乳液，无法确定其所有人，下一步将按照《市场监督管理行政处罚程序规定》的规定开展案件调查。\n35万\n广州一公司因虚假宣传被罚\n近日，信用广州公布的一则行政处罚信息显示，广州市北诗化妆品有限公司在宣传商品时，使用“嫩白祛黑”“86%试用者嘴唇明显粉嫩诱人”“ 抑制细菌 ” 等广告内容，且无法提供广告的相关依据，涉嫌使用医疗用语或易使推销的商品与药品、医疗器械相混淆的用语，被处以罚款35万元。\n根据《中华人民共和国广告法》第十一条第二款规定，广告使用数据、统计资料、调查结果、文摘、引用语等引证内容的，应当真实、准确，并表明出处。\n\n",
        "Recommendation_links": [
            "https://new.qq.com/rain/a/20221130A06Q1F00",
            null,
            "https://new.qq.com/rain/a/20221130A050XV00",
            "https://new.qq.com/rain/a/20221130A05SGP00",
            "https://new.qq.com/rain/a/20221130A04QCH00",
            "https://new.qq.com/rain/a/20221130A03YGM00",
            "https://new.qq.com/rain/a/20221130A05BQX00",
            "https://new.qq.com/rain/a/UTR2022113000035500",
            "https://new.qq.com/rain/a/20221130A05QZU00",
            "https://new.qq.com/rain/a/20221130A06WEU00",
            "https://new.qq.com/rain/a/20221130A076C300",
            "https://new.qq.com/rain/a/20221130A06X9P00",
            "https://new.qq.com/rain/a/20221130A06IMV00",
            "https://new.qq.com/rain/a/20221130A05Y4I00",
            "https://new.qq.com/rain/a/UTR2022090700068100",
            "https://new.qq.com/rain/a/20221130A05UCR00",
            "https://new.qq.com/rain/a/20221130A068NV00",
            "https://new.qq.com/rain/a/20221130V02Z4S00",
            "https://new.qq.com/rain/a/20221130A0411R00",
            "https://new.qq.com/rain/a/UTR2022090700067800",
            "https://new.qq.com/rain/a/20221130A01QQQ00",
            "https://new.qq.com/rain/a/UTR2022112000014600",
            "https://new.qq.com/rain/a/20221130A04IP400",
            "https://new.qq.com/rain/a/20221130A05GZJ00",
            "https://new.qq.com/rain/a/20221130A0529V00",
            "https://new.qq.com/rain/a/20221130A03BQR00",
            null,
            "https://new.qq.com/rain/a/20221129V02NWN00",
            "https://new.qq.com/rain/a/20221130A044X800",
            "https://new.qq.com/rain/a/20221130A041CD00",
            "https://new.qq.com/rain/a/UTR2022110100035500",
            "https://new.qq.com/rain/a/20221130A031F400",
            "https://new.qq.com/rain/a/20221129A085D800",
            "https://new.qq.com/rain/a/20221130A0256J00",
            "https://new.qq.com/rain/a/UTR2022112800023400",
            "https://new.qq.com/rain/a/20221130A01OOS00",
            "https://new.qq.com/rain/a/20221129A0AA9J00",
            "https://new.qq.com/rain/a/20221130A026K100",
            "https://new.qq.com/rain/a/20221130A0280600",
            "https://new.qq.com/rain/a/20221130A023RT00",
            "https://new.qq.com/rain/a/20221130V0252V00",
            "https://new.qq.com/rain/a/20221130A01NLE00",
            "https://new.qq.com/rain/a/20221130A00X2000",
            "https://new.qq.com/rain/a/20221129A0766Y00",
            "https://new.qq.com/rain/a/20221129A0AFDS00",
            null,
            "https://new.qq.com/rain/a/UTR2022090700070900",
            "https://new.qq.com/rain/a/20221130A0130J00",
            "https://new.qq.com/rain/a/20221130A00S8Z00",
            "https://new.qq.com/rain/a/20221129A09Y3Z00",
            "https://new.qq.com/rain/a/20221129A0A2OS00",
            "https://new.qq.com/rain/a/20221129A09OIJ00",
            "https://new.qq.com/rain/a/20221129A09X7V00",
            "https://new.qq.com/rain/a/20221130A004HB00",
            "https://new.qq.com/rain/a/20221129A099OE00",
            "https://new.qq.com/rain/a/20221129A0881Q00",
            "https://new.qq.com/rain/a/20221129A09UD600",
            "https://new.qq.com/rain/a/20221129V05ZLY00",
            "https://new.qq.com/rain/a/20221129A0A4Z400",
            "https://new.qq.com/rain/a/20221129A08BJE00",
            "https://new.qq.com/rain/a/20221129A0A0E500",
            "https://new.qq.com/rain/a/20221129A0AFJ500",
            "https://new.qq.com/rain/a/20221129A044TH00",
            "https://new.qq.com/rain/a/20221129A09K8I00",
            "https://new.qq.com/rain/a/20221129A09JL000",
            "https://new.qq.com/rain/a/20221129A09MKT00",
            "https://new.qq.com/rain/a/20221129A09I5C00",
            "https://new.qq.com/rain/a/20221129A05NKS00",
            "https://new.qq.com/rain/a/20221129A09KC800",
            "https://new.qq.com/rain/a/20221129A09DX300",
            "https://new.qq.com/rain/a/20221129A09E6X00",
            "https://new.qq.com/rain/a/20221129A09ECX00",
            "https://new.qq.com/rain/a/20221129A08Y3600",
            "https://new.qq.com/rain/a/20221129A095S200",
            "https://new.qq.com/rain/a/20221129A090LU00",
            "https://new.qq.com/rain/a/20221129A07YYN00",
            "https://new.qq.com/rain/a/20221129A08E4300",
            "https://new.qq.com/rain/a/20221129A087LZ00",
            "https://new.qq.com/rain/a/20221129A0843700",
            "https://new.qq.com/rain/a/20221129A08BJ900",
            "https://new.qq.com/rain/a/20221129A07MXZ00",
            "https://new.qq.com/rain/a/20221129A03VGY00",
            "https://new.qq.com/rain/a/UTR2022112900029900",
            "https://new.qq.com/rain/a/20221129A0706L00",
            "https://new.qq.com/rain/a/20221129A06T9Q00",
            "https://new.qq.com/rain/a/20221129A06GI600",
            "https://new.qq.com/rain/a/20221129A036U800",
            "https://new.qq.com/rain/a/20221129V06FY500",
            "https://new.qq.com/rain/a/20221129A03Y5K00",
            "https://new.qq.com/rain/a/20221129V05XXY00",
            "https://new.qq.com/rain/a/20221129V06EY200",
            "https://new.qq.com/rain/a/20221129A06LRT00",
            "https://new.qq.com/rain/a/20221129A06DT100",
            "https://new.qq.com/rain/a/20221129A060NU00",
            "https://new.qq.com/rain/a/20221129A05L8000",
            "https://new.qq.com/rain/a/20221129V021AM00",
            "https://new.qq.com/rain/a/20221129A04BS100",
            "https://new.qq.com/rain/a/20221129A04WCP00",
            "https://new.qq.com/rain/a/20221129A04QXV00",
            "https://new.qq.com/rain/a/20221129A04Y4M00",
            "https://new.qq.com/rain/a/FIN2022112800046900",
            "https://new.qq.com/rain/a/20221129A041RR00",
            "https://new.qq.com/rain/a/20221129A00X4800",
            "https://new.qq.com/rain/a/20221129A02MF800",
            "https://new.qq.com/rain/a/20221129A00UYX00",
            "https://new.qq.com/rain/a/20221129A021TD00",
            "https://new.qq.com/rain/a/20221129A004QB00",
            "https://new.qq.com/rain/a/20221129A00WDA00",
            "https://new.qq.com/rain/a/20221129A01G3V00",
            "https://new.qq.com/rain/a/20221128V01D3900",
            "https://new.qq.com/rain/a/20221129A014HF00",
            "https://new.qq.com/rain/a/20221129A00ITV00",
            "https://new.qq.com/rain/a/20221129A00J1000",
            "https://new.qq.com/rain/a/20221128A0A4Q700",
            "https://new.qq.com/rain/a/20221129A00OOH00",
            "https://new.qq.com/rain/a/20221129A0048Y00",
            "https://new.qq.com/rain/a/20221128A08ERC00",
            "https://new.qq.com/rain/a/20221128A084PK00",
            "https://new.qq.com/rain/a/20221128A08SDK00",
            "https://new.qq.com/rain/a/20221129A00G4H00",
            "https://new.qq.com/rain/a/20221128A09V0300",
            "https://new.qq.com/rain/a/20221128A0A71300",
            "https://new.qq.com/rain/a/20221128A082AA00",
            "https://new.qq.com/rain/a/20221128A069ZV00",
            "https://new.qq.com/rain/a/20221128A082EX00",
            "https://new.qq.com/rain/a/20221128A09J1I00",
            "https://new.qq.com/rain/a/20221128A0A24400",
            "https://new.qq.com/rain/a/20221128A09WVD00",
            "https://new.qq.com/rain/a/20221128A087BZ00",
            "https://new.qq.com/rain/a/20221128A099GW00",
            "https://new.qq.com/rain/a/20221128A09GEJ00",
            "https://new.qq.com/rain/a/20221128A05ITC00",
            "https://new.qq.com/rain/a/20221128A07N3000",
            "https://new.qq.com/rain/a/20221128A08AFA00",
            "https://new.qq.com/rain/a/20221128A08B9T00",
            "https://new.qq.com/rain/a/20221128A08F0300",
            "https://new.qq.com/rain/a/20221128A08DL900",
            "https://new.qq.com/rain/a/20221128A08DZF00",
            "https://new.qq.com/rain/a/20221128A08GR500",
            "https://new.qq.com/rain/a/20221128A08N0E00",
            "https://new.qq.com/rain/a/20221128A08LQG00",
            "https://new.qq.com/rain/a/20221128A08NQ500",
            "https://new.qq.com/rain/a/20221128A08OPM00",
            "https://new.qq.com/rain/a/20221128A08QQM00",
            "https://new.qq.com/rain/a/20221128A08QY300",
            "https://new.qq.com/rain/a/20221128A08DBU00",
            "https://new.qq.com/rain/a/20221128A07OMG00",
            "https://new.qq.com/rain/a/20221128A01H4I00",
            "https://new.qq.com/rain/a/20221128A07N2Z00",
            "https://new.qq.com/rain/a/20221128A02V0300",
            "https://new.qq.com/rain/a/20221128A05PBS00",
            "https://new.qq.com/rain/a/20221128A06O5U00",
            "https://new.qq.com/rain/a/20221128A06UQR00",
            "https://new.qq.com/rain/a/20221128A06FD900",
            "https://new.qq.com/rain/a/20221128V06WPV00",
            "https://new.qq.com/rain/a/20221128A06SOG00",
            "https://new.qq.com/rain/a/20221128A06J6300",
            "https://new.qq.com/rain/a/20221128A0603S00",
            "https://new.qq.com/rain/a/20221128A05NP100",
            "https://new.qq.com/rain/a/20221128A04VTB00",
            "https://new.qq.com/rain/a/20221128A05D2900",
            "https://new.qq.com/rain/a/20221128A04YRN00",
            "https://new.qq.com/rain/a/20221128A05STT00",
            "https://new.qq.com/rain/a/20221128A05HO300",
            "https://new.qq.com/rain/a/20221128A05IDF00",
            "https://new.qq.com/rain/a/20221128A05TKC00",
            "https://new.qq.com/rain/a/20221128A013DQ00",
            "https://new.qq.com/rain/a/20221128A05T5Y00",
            "https://new.qq.com/rain/a/20221128A05BXP00",
            "https://new.qq.com/rain/a/20221128A05APP00",
            "https://new.qq.com/rain/a/20221128A02TQD00",
            "https://new.qq.com/rain/a/20221128A03WN800",
            "https://new.qq.com/rain/a/20221128V04BCC00",
            "https://new.qq.com/rain/a/20221128A03E8V00",
            "https://new.qq.com/rain/a/20221128A04L2U00",
            "https://new.qq.com/rain/a/20221128A03O1Q00",
            "https://new.qq.com/rain/a/20221128A04MMO00",
            "https://new.qq.com/rain/a/20221128A04C2A00",
            "https://new.qq.com/rain/a/20221128A04L5M00",
            "https://new.qq.com/rain/a/20221128A02DCP00",
            "https://new.qq.com/rain/a/20221128A02OHM00",
            "https://new.qq.com/rain/a/20221128A03SIN00",
            "https://new.qq.com/rain/a/20221128A007TS00",
            "https://new.qq.com/rain/a/20221128A03MSF00",
            "https://new.qq.com/rain/a/20221128A030PT00",
            "https://new.qq.com/rain/a/20221128A03QW400",
            "https://new.qq.com/rain/a/20221128A03W4P00",
            "https://new.qq.com/rain/a/20221128A00YDP00",
            "https://new.qq.com/rain/a/20221128A0308E00",
            "https://new.qq.com/rain/a/20221128A01X2K00",
            "https://new.qq.com/rain/a/20221128A02LRO00",
            "https://new.qq.com/rain/a/20221128A02NVP00",
            "https://new.qq.com/rain/a/20221128V02JLM00",
            "https://new.qq.com/rain/a/20221128A00ZHH00",
            "https://new.qq.com/rain/a/20221128A02C4P00",
            "https://new.qq.com/rain/a/20221128A0262L00",
            "https://new.qq.com/rain/a/20221128A014B500",
            "https://new.qq.com/rain/a/20221128A020FZ00",
            "https://new.qq.com/rain/a/20221128A020CW00",
            "https://new.qq.com/rain/a/20221128A00H2T00",
            "https://new.qq.com/rain/a/20221124A058I200",
            "https://new.qq.com/rain/a/20221128A01RSI00"
        ]
    }
}