{
    "110": {
        "Tag": "digital",
        "Id": "20221130A0A4PU00_115",
        "Url": "https://new.qq.com/omn/20221130/20221130A0A4PU00.html",
        "Title": "荣耀发布第二款折叠屏手机，CEO赵明：量的提升或改善成本问题",
        "Author": "界面新闻",
        "Publish_Date": "2022-11-30",
        "Post_time": "22:49",
        "Content": "记者｜陆柯言\n11月30日，荣耀折叠屏手机Magic Vs正式发售，售价7499元起。这是暨OPPO Find X、华为Pocket系列之后，又一款价格打至8000元以内的主流折叠屏手机。荣耀CEO赵明在接受界面新闻采访时表示，希望能够在这一价位直接与华为、苹果的旗舰机型竞争。\n作为荣耀旗舰系列之一，Magic Vs基本搭载了其最高配置，包括4nm制程的骁龙8+芯片，自研操作系统Magic OS 7.0等。\n具体来看，Magic Vs内置多个荣耀自研的核心部件，包括“鲁班0齿轮铰链”技术，其释放的空间令器件数量得以大幅减少，重量也降低62%，达到261g，接近直板机水平。此外，荣耀也把更多空间留给了电池，电池容量达5000mAh。\n软件适配度是决定折叠屏手机能否成为主力机的关键。除常用软件的适配外，Magic Vs实现了Top200视频APP的全面适配，并适配了股票类APP和WPS等办公类软件的大屏显示。\n这是荣耀发布的第二款折叠屏手机。至此，中国头部手机厂商中，华为、vivo、小米、荣耀等厂商均已完成折叠屏手机的更新换代，而折叠屏手机也在刚刚过去的三季度中创下中国市场有史以来最大单季出货量。来自IDC的最新统计显示，2022年第三季度，中国折叠屏产品出货量超过100万台，同比增幅约246%。其中，华为以近半份额占据第一，荣耀位列第五。\n赵明认为，折叠屏手机已经进入主力机时代，但在未来很长一段时间内仍然会和直板机同时存在，有很多技术需要突破，包括重量、续航、性能、热设计、可靠性和应用丰富程度等，尤其是革新式的应用体验至今仍未出现。\n尽管铰链等核心技术的成熟，已经让折叠屏从最初动辄两万元的定价降至一半，但其设计和制造成本相对直板机仍属高位。赵明提到，如果不考虑量，目前的定价对荣耀来说是“透支”的，这也是行业的普遍现象，像华为折叠屏产品Mate Xs亏损就超过6000万美元。\n不过，赵明对Magic Vs的销量预期很乐观，也相信量的提升可以更好地解决成本问题。他预计到2023年，5000元以上的手机出货量大概会在4000万至5000万台，其中20%-30%都会是折叠屏，而荣耀的市场份额还将继续提升。\n",
        "Recommendation_links": NaN
    }
}