{
    "72": {
        "Tag": "security",
        "Id": "20221128A00QG1_76",
        "Url": "https://new.qq.com/rain/a/20221128A00QG100",
        "Title": "突发爆雷！今天国际实控人、董事长被监视居住",
        "Author": "第一财经",
        "Publish_Date": "2022-11-28",
        "Post_time": "07:29",
        "Content": "11月27日晚间，今天国际发布公告称，公司实控人、董事长邵健伟因涉嫌为他人掩饰、隐瞒犯罪所得被公安机关指定居所监视居住。\n今天国际是一家专业的智慧物流和智能制造系统综合解决方案提供商。据此前公告，比亚迪、宁德时代、欣旺达是公司重要客户。\n截至11月25日，今天国际报18.03元/股，今年以来股价涨幅为63.64%。\n图片来源：Wind\n实控人涉嫌为他人掩饰隐瞒犯罪所得\n11月27日晚间，今天国际发布公告称，11月26日接到公司实际控制人、董事长邵健伟的家属通知，邵健伟因涉嫌为他人掩饰、隐瞒犯罪所得被公安机关指定居所监视居住，相关事项尚待进一步调查。\n图片来源：公司公告\n同时，今天国际表示，公司拥有完善的治理结构及内部控制机制，日常经营管理由公司高管团队负责，目前公司生产经营正常，各项工作有序开展。\n今天国际第四届董事会、监事会成员原本是2022年11月22日任期届满。公司11月18日发布公告称，鉴于公司董事会及监事会换届工作尚在积极推进中，为确保公司董事会、监事会相关工作的连续性和稳定性，公司第五届董事会和监事会换届选举工作将适当延期。\n资料显示，邵健伟，中国国籍，拥有香港居民身份证，1971年生，从2010年起连任今天国际四届董事会董事长。\n公司2022年半年报显示，邵健伟直接持有公司35.47%股权，同时作为执行事务合伙人持有深圳市华锐丰投资合伙企业（有限合伙）68.8%的财产份额，深圳市华锐丰投资合伙企业（有限合伙）持有公司2.82%股权，由此，邵健伟合计持有公司37.41%的股权，对公司的表决权比例为38.29%。\n三大行业订单持续增长\n今天国际是一家专业的智慧物流和智能制造系统综合解决方案提供商，为生产制造、流通配送企业提供自动化生产线及物流系统的规划设计、系统集成、软件开发、设备定制、电控系统开发、现场安装调试、客户培训和售后服务等一体化业务。其产品已应用于烟草、新能源、冷链、石化等众多行业。\n公司2022年第三季度实现营收5.23亿元，同比增长78.56%；归母净利润8100万元，同比增长350.41%；前三季度实现营收16.86亿元，同比增长89.32%；归母净利润1.88亿元，同比增长229.16%。\n公司今年前三季度营收规模已超过去年全年，净利润超过去年全年的两倍。对于前三季度业绩的增长，公司表示，主要是报告期内完成的项目数量及金额规模同比有较大幅度增加所致。\n今年上半年，今天国际在新能源锂电行业、烟草行业及石化行业订单持续增长，持续获得了比亚迪、宁德时代、欣旺达等新能源行业重要客户的订单。上半年共取得新能源行业订单13.69亿元，同比增长12.92%。\n今天国际日前在调研纪要中表示，今天国际有订单的下游行业已经超过30个，新能源只是其中之一。从自动化业务来看，国内市场渗透率还相当低，相比国际市场，国内尚有很大的市场空间，如果新能源行业未来的景气度下降，公司可以通过在其他下游行业的业务发展来保障业绩。\n编辑：陈健健 王寅\n",
        "Recommendation_links": [
            "https://new.qq.com/rain/a/20221130A0A93T00",
            null,
            "https://new.qq.com/rain/a/20221201A0030300",
            "https://new.qq.com/rain/a/20221201A003Z100",
            "https://new.qq.com/rain/a/UTR2022090700067800",
            "https://new.qq.com/rain/a/UTR2022090700068100",
            "https://new.qq.com/rain/a/UTR2022112800023400",
            null,
            "https://new.qq.com/rain/a/20221201A01MZN00",
            "https://new.qq.com/rain/a/20221201V028KM00",
            "https://new.qq.com/rain/a/20221201A002UC00",
            "https://new.qq.com/rain/a/20221201A0046L00",
            "https://new.qq.com/rain/a/UTR2022090700070900",
            null,
            "https://new.qq.com/rain/a/20221201A00BNH00",
            "https://new.qq.com/rain/a/20221201A00IR400",
            "https://new.qq.com/rain/a/20221130A0AEM300",
            "https://new.qq.com/rain/a/20221130A07LVS00",
            "https://new.qq.com/rain/a/20221130A06WTL00",
            null,
            "https://new.qq.com/rain/a/20221201A0056R00",
            "https://new.qq.com/rain/a/20221201A001HI00",
            "https://new.qq.com/rain/a/20221201A00E6700",
            "https://new.qq.com/rain/a/20221201A00QEY00",
            "https://new.qq.com/rain/a/20221130A07L5500",
            "https://new.qq.com/rain/a/UTR2022113000035500",
            "https://new.qq.com/rain/a/20221201A00FXN00",
            "https://new.qq.com/rain/a/20221130A0A7I000",
            "https://new.qq.com/rain/a/20221130A0A03500",
            null,
            "https://new.qq.com/rain/a/20221130A0A1JV00",
            "https://new.qq.com/rain/a/20221130V09QFG00",
            "https://new.qq.com/rain/a/20221130A09F2E00",
            "https://new.qq.com/rain/a/20221129A06O3S00",
            "https://new.qq.com/rain/a/20221130A098LA00",
            "https://new.qq.com/rain/a/20221130A08T7K00",
            "https://new.qq.com/rain/a/20221130A08YY200",
            "https://new.qq.com/rain/a/20221130A08Z2D00",
            "https://new.qq.com/rain/a/20221130A03YGM00",
            "https://new.qq.com/rain/a/20221130A090IW00",
            "https://new.qq.com/rain/a/20221130A092MR00",
            "https://new.qq.com/rain/a/20221130A05QZU00",
            "https://new.qq.com/rain/a/20221130A04QCH00",
            "https://new.qq.com/rain/a/20221130A08HZN00",
            "https://new.qq.com/rain/a/20221130A0872B00",
            "https://new.qq.com/rain/a/20221130A05BQX00",
            "https://new.qq.com/rain/a/20221130A0876800",
            "https://new.qq.com/rain/a/20221130A0735500",
            null,
            "https://new.qq.com/rain/a/20221130A0795N00",
            "https://new.qq.com/rain/a/20221130A07LY200",
            "https://new.qq.com/rain/a/20221130A07LJ400",
            "https://new.qq.com/rain/a/20221130A07XFG00",
            "https://new.qq.com/rain/a/20221130A07XLE00",
            "https://new.qq.com/rain/a/20221130A080FT00",
            "https://new.qq.com/rain/a/20221130A0808900",
            "https://new.qq.com/rain/a/20221130A080BP00",
            "https://new.qq.com/rain/a/20221130A07Z7E00",
            null,
            "https://new.qq.com/rain/a/20221130A07LUM00",
            "https://new.qq.com/rain/a/20221130A06WEU00",
            "https://new.qq.com/rain/a/20221130A076C300",
            "https://new.qq.com/rain/a/20221130A06X9P00",
            "https://new.qq.com/rain/a/20221130A06IMV00",
            "https://new.qq.com/rain/a/20221130A05Y4I00",
            "https://new.qq.com/rain/a/20221130A06Q1F00",
            "https://new.qq.com/rain/a/20221130A05UCR00",
            "https://new.qq.com/rain/a/20221130A068NV00",
            null,
            "https://new.qq.com/rain/a/20221130V02Z4S00",
            "https://new.qq.com/rain/a/20221130A0411R00",
            "https://new.qq.com/rain/a/20221130A05SGP00",
            "https://new.qq.com/rain/a/20221130A01QQQ00",
            "https://new.qq.com/rain/a/UTR2022112000014600",
            "https://new.qq.com/rain/a/20221130A04IP400",
            "https://new.qq.com/rain/a/20221130A05GZJ00",
            "https://new.qq.com/rain/a/20221130A050XV00",
            "https://new.qq.com/rain/a/20221130A0529V00",
            "https://new.qq.com/rain/a/20221130A03BQR00",
            "https://new.qq.com/rain/a/20221129V02NWN00",
            "https://new.qq.com/rain/a/20221130A044X800",
            "https://new.qq.com/rain/a/20221130A041CD00",
            "https://new.qq.com/rain/a/UTR2022110100035500",
            "https://new.qq.com/rain/a/20221130A031F400",
            "https://new.qq.com/rain/a/20221129A085D800",
            "https://new.qq.com/rain/a/20221130A0256J00",
            "https://new.qq.com/rain/a/20221130A01OOS00",
            "https://new.qq.com/rain/a/20221129A0AA9J00",
            "https://new.qq.com/rain/a/20221130A026K100",
            "https://new.qq.com/rain/a/20221130A0280600",
            "https://new.qq.com/rain/a/20221130A023RT00",
            "https://new.qq.com/rain/a/20221130V0252V00",
            "https://new.qq.com/rain/a/20221130A01NLE00",
            "https://new.qq.com/rain/a/20221130A00X2000",
            "https://new.qq.com/rain/a/20221129A0766Y00",
            "https://new.qq.com/rain/a/20221129A0AFDS00",
            "https://new.qq.com/rain/a/20221130A0130J00",
            "https://new.qq.com/rain/a/20221130A00S8Z00",
            "https://new.qq.com/rain/a/20221129A09Y3Z00",
            "https://new.qq.com/rain/a/20221129A0A2OS00",
            "https://new.qq.com/rain/a/20221129A09OIJ00",
            "https://new.qq.com/rain/a/20221129A09X7V00",
            "https://new.qq.com/rain/a/20221130A004HB00",
            "https://new.qq.com/rain/a/20221129A099OE00",
            "https://new.qq.com/rain/a/20221129A0881Q00",
            "https://new.qq.com/rain/a/20221129A09UD600",
            "https://new.qq.com/rain/a/20221129V05ZLY00",
            "https://new.qq.com/rain/a/20221129A0A4Z400",
            "https://new.qq.com/rain/a/20221129A08BJE00",
            "https://new.qq.com/rain/a/20221129A0A0E500",
            "https://new.qq.com/rain/a/20221129A0AFJ500",
            "https://new.qq.com/rain/a/20221129A044TH00",
            "https://new.qq.com/rain/a/20221129A09K8I00",
            "https://new.qq.com/rain/a/20221129A09JL000",
            "https://new.qq.com/rain/a/20221129A09MKT00",
            "https://new.qq.com/rain/a/20221129A09I5C00",
            "https://new.qq.com/rain/a/20221129A05NKS00",
            "https://new.qq.com/rain/a/20221129A09KC800",
            "https://new.qq.com/rain/a/20221129A09DX300",
            "https://new.qq.com/rain/a/20221129A09E6X00",
            "https://new.qq.com/rain/a/20221129A09ECX00",
            "https://new.qq.com/rain/a/20221129A08Y3600",
            "https://new.qq.com/rain/a/20221129A095S200",
            "https://new.qq.com/rain/a/20221129A090LU00",
            "https://new.qq.com/rain/a/20221129A07YYN00",
            "https://new.qq.com/rain/a/20221129A08E4300",
            "https://new.qq.com/rain/a/20221129A087LZ00",
            "https://new.qq.com/rain/a/20221129A0843700",
            "https://new.qq.com/rain/a/20221129A08BJ900",
            "https://new.qq.com/rain/a/20221129A07MXZ00",
            "https://new.qq.com/rain/a/20221129A03VGY00",
            "https://new.qq.com/rain/a/UTR2022112900029900",
            "https://new.qq.com/rain/a/20221129A0706L00",
            "https://new.qq.com/rain/a/20221129A06T9Q00",
            "https://new.qq.com/rain/a/20221129A06GI600",
            "https://new.qq.com/rain/a/20221129A036U800",
            "https://new.qq.com/rain/a/20221129V06FY500",
            "https://new.qq.com/rain/a/20221129A03Y5K00",
            "https://new.qq.com/rain/a/20221129V05XXY00",
            "https://new.qq.com/rain/a/20221129V06EY200",
            "https://new.qq.com/rain/a/20221129A06LRT00",
            "https://new.qq.com/rain/a/20221129A06DT100",
            "https://new.qq.com/rain/a/20221129A060NU00",
            "https://new.qq.com/rain/a/20221129A05L8000",
            "https://new.qq.com/rain/a/20221129V021AM00",
            "https://new.qq.com/rain/a/20221129A04BS100",
            "https://new.qq.com/rain/a/20221129A04WCP00",
            "https://new.qq.com/rain/a/20221129A04QXV00",
            "https://new.qq.com/rain/a/20221129A04Y4M00",
            "https://new.qq.com/rain/a/FIN2022112800046900",
            "https://new.qq.com/rain/a/20221129A041RR00",
            "https://new.qq.com/rain/a/20221129A00X4800",
            "https://new.qq.com/rain/a/20221129A02MF800",
            "https://new.qq.com/rain/a/20221129A00UYX00",
            "https://new.qq.com/rain/a/20221129A021TD00",
            "https://new.qq.com/rain/a/20221129A004QB00",
            "https://new.qq.com/rain/a/20221129A00WDA00",
            "https://new.qq.com/rain/a/20221129A01G3V00",
            "https://new.qq.com/rain/a/20221128V01D3900",
            "https://new.qq.com/rain/a/20221129A014HF00",
            "https://new.qq.com/rain/a/20221129A00ITV00",
            "https://new.qq.com/rain/a/20221129A00J1000",
            "https://new.qq.com/rain/a/20221128A0A4Q700",
            "https://new.qq.com/rain/a/20221129A00OOH00",
            "https://new.qq.com/rain/a/20221129A0048Y00",
            "https://new.qq.com/rain/a/20221128A08ERC00",
            "https://new.qq.com/rain/a/20221128A084PK00",
            "https://new.qq.com/rain/a/20221128A08SDK00",
            "https://new.qq.com/rain/a/20221129A00G4H00",
            "https://new.qq.com/rain/a/20221128A09V0300",
            "https://new.qq.com/rain/a/20221128A0A71300",
            "https://new.qq.com/rain/a/20221128A082AA00",
            "https://new.qq.com/rain/a/20221128A069ZV00",
            "https://new.qq.com/rain/a/20221128A082EX00",
            "https://new.qq.com/rain/a/20221128A09J1I00",
            "https://new.qq.com/rain/a/20221128A0A24400",
            "https://new.qq.com/rain/a/20221128A09WVD00",
            "https://new.qq.com/rain/a/20221128A087BZ00",
            "https://new.qq.com/rain/a/20221128A099GW00",
            "https://new.qq.com/rain/a/20221128A09GEJ00",
            "https://new.qq.com/rain/a/20221128A05ITC00",
            "https://new.qq.com/rain/a/20221128A07N3000",
            "https://new.qq.com/rain/a/20221128A08AFA00",
            "https://new.qq.com/rain/a/20221128A08B9T00",
            "https://new.qq.com/rain/a/20221128A08F0300",
            "https://new.qq.com/rain/a/20221128A08DL900",
            "https://new.qq.com/rain/a/20221128A08DZF00",
            "https://new.qq.com/rain/a/20221128A08GR500",
            "https://new.qq.com/rain/a/20221128A08N0E00",
            "https://new.qq.com/rain/a/20221128A08LQG00",
            "https://new.qq.com/rain/a/20221128A08NQ500",
            "https://new.qq.com/rain/a/20221128A08OPM00",
            "https://new.qq.com/rain/a/20221128A08QQM00",
            "https://new.qq.com/rain/a/20221128A08QY300",
            "https://new.qq.com/rain/a/20221128A08DBU00",
            "https://new.qq.com/rain/a/20221128A07OMG00",
            "https://new.qq.com/rain/a/20221128A01H4I00",
            "https://new.qq.com/rain/a/20221128A07N2Z00",
            "https://new.qq.com/rain/a/20221128A02V0300",
            "https://new.qq.com/rain/a/20221128A05PBS00",
            "https://new.qq.com/rain/a/20221128A06O5U00",
            "https://new.qq.com/rain/a/20221128A06FD900",
            "https://new.qq.com/rain/a/20221128V06WPV00",
            "https://new.qq.com/rain/a/20221128A06SOG00",
            "https://new.qq.com/rain/a/20221128A06J6300",
            "https://new.qq.com/rain/a/20221128A0603S00",
            "https://new.qq.com/rain/a/20221128A05NP100"
        ]
    }
}