{
    "152": {
        "Tag": "security",
        "Id": "20221123A07ACE_156",
        "Url": "https://new.qq.com/rain/a/20221123A07ACE00",
        "Title": "招商证券再破“A股魔咒”调侃，张夏建议布局“新时代五朵金花”",
        "Author": "大A透视镜",
        "Publish_Date": "2022-11-23",
        "Post_time": "18:18",
        "Content": "财联社11月23日讯（记者 封其娟）行至年末，多份2023年度投资策略报告于11月开始集中发布，各家券商的2023年年度策略会也在陆续召开。身为A股“魔咒”之一，招商证券策略会自是备受市场关注。继年中打破“魔咒”后，“魔咒”效应式微。经过一日震荡整理，沪指今日收盘录得上涨0.26%，深证成指、创业板指分别下跌0.27%、0.14%。\n11月23日-24日，招商证券在上海召开了主题为“新征程、再出发”的2023资本市场年会，发布年度宏观经济、A股市场、行业等系列投资策略报告。同时，招商研究团队携手近600家上市公司、60余位演讲嘉宾和行业专家，搭建交流平台，挖掘经济转型阶段的投资机会。策略会交流互动形式多样，既有大会场和分会场深度研讨，也有上市公司小范围或一对一交流。\n\n会上，招商证券首席宏观分析师张静静发表了年度宏观研究观点，认为资产的盈利因子看国内，而资产的估值因子看海外。在演讲中，张静静指出“全球在三月份开始的变局就没有破，有没有可能出现破局的结果，其实就是看未来中国的经济和美国的货币政策”。\n\n紧接着，招商证券策略首席分析师张夏发表了2023年投资策略观点，认为2023年A股进入中期反转的结构性震荡上行周期，走势类似“N”型走势。进入新一轮五年周期后，A股的投资思路、选股模式都会发生重大变化，需要更加重视科技自立自强，能够实现安全发展、迈向制造业高端化、聚焦硬科技的专精特新成长标的。\n\n关于行业和产业趋势，张夏建议围绕以高端制造、医疗医药、新能源、自主可控、军工装备（高医新自军）为代表的“新时代五朵金花”进行重点布局。兼顾稳地产带来的龙头地产和地产链消费的阶段性机会。偏中小成长风格相对占优，年度关注指数科创50、北证50、创业板综。\n张静静：盈利因子将转好，估值因子将修复\n在张静静看来，2023年中国经济回升，盈利因子将转好。\n2023年国内宏观两条主线即发展和安全。疫情形势的边际变化对发展的总量和结构特征有决定性意义，然而现实路径走向仍有不确定性；相比之下，安全线索的持续推进是大概率事件。\n张静静预计明年实际增长目标或为4.5%。考虑到明年出口下台阶、财政压力较大等因素，稳内需重要性显著提升。假设疫情形势基本不变，达成目标的挑战性相当大；而假设疫情形势向有利于恢复经济的方向变化，消费的潜力有望释放，达成目标的概率更高。\n现实的路径，存在由情景一向情景二过渡的可能性，伴随疫苗、药品、器械等公共卫生资源的积极储备，以及对事态发展的动态评估，是一个从0向1推进的过程。与发展同等重要的是安全，是明年确定性较高的宏观线索，有望带来部分产业方向的α机会。\n\n张静静指出，2023年美联储加息结束、开启降息，估值因子将修复。\n美联储或已用力过猛，继续大幅加息，美国将面临硬着陆风险，具体表现在：\n1）经济衰退初期特征显现。Q2以来小企业景气率先转弱，制造业先于非制造业放缓；\n2）消费动能或将快速衰减；\n3）主动去库存或延续至明年Q3；\n4）投资放缓，房地产继续掣肘经济但也缓和通胀压力；\n5）预计美国2023年实际GDP增速降至-1.2%，低点在Q3。\n张静静认为，2022年美国经济的相对优势助推美元强劲，但2023年该局面将逆转。通过对照美国、欧洲、日本与韩国，张静静直言，不难看出2022年美国经济最强、欧韩次之，日本最弱。\n张静静谈到，美国经济有三点优势：\n1）人口相对其他发达经济体最年轻；\n2）全面躺平，产能利用率恢复如初；\n3）周边各国亦基本“躺平”，旅游业恢复较好。\n而欧洲与韩国的共性和差异均有两点。在共性上，一是全面躺平，产能利用率恢复如初；二是人口年龄中位数相当，但高于美国。同时，差异在于周边国家的防疫开放程度不同，俄乌冲突或令欧洲承受的成本压力高于韩国。\n日本经济疲软或源于三个方面：\n1）人口老龄化程度极高；\n2）或因老龄化而未彻底躺平，进而生产端尚未复原；\n3）周边国家仍然严格防疫。2022年美国或已耗尽所有疫后经济红利。\n2023年俄乌因素对欧洲掣肘缓解，随着亚洲各国疫情相继降温日韩出入境人数快速恢复，亚洲经济内生动能亦将改善。一旦美国相对优势锐减，美元指数大概率见顶回落。\n关于2023年，张静静认为美国通胀有望加速回落，中美联储或将考虑降息。并指出美国疫后高通胀与四因素有关：供需矛盾、货币效应、能源革命以及劳动力成本上升，分别反映在美国CPI中的二手车等耐用品分项、房租分项、能源分项以及医疗等服务分项。而上述核心矛盾都已逆转。\n\n在张静静看来，下个春天美联储或将结束加息，明年中有望考虑降息。美债进入牛市，美元顶部回落，新兴跑赢美股，A股配置价值凸现。\n总体而言，张静静团队认为2023年全球大类资产表现排序为：A股、H股>有色、黑色等商品>美债>美股、黄金>能源>A债。\n张夏：建议重点布局“新时代五朵金花”\n张夏团队在报告中提出党的二十大报告指明未来五年的核心思路，A股从重视龙头（“各种茅”）、高现金流的投资思路，在经历了两年相对混乱的结构之后，有望围绕科技自立自强、安全发展，高端制造、硬科技、专精特新五个关键词构建新的选股思路。可以考虑进行重点布局高端制造、医疗医药、新能源、自主可控、军工装备（高医新自军）等“新时代五朵金花”。\n国内经济方面，在2023年，预计在稳地产、基建和制造业继续发力的共振之下，中长期社融有望重回上行趋势，企业盈利增速进入回升周期，进入2023年后，整体A股盈利增速有望边际改善，预计全年全部A股和非金融及两油盈利同比增速测算值分别为7.3%/9.5%。A股也将会回到2022年二季度开启的上行周期。医疗新基建和数字新基建也可能成为稳增长的弹性方向。但考虑到增量资金相对有限且有外部的一些风险和压力。2023年整体将会类似2003、20 13年一样，呈现逢三逢四结构牛特征。\n\n在细分产业趋势方面，张夏团队建议投资者关注4大细分方向：\n1）绿色低碳方面关注复合集流体、大储、类储能、便携式储能、钠电池、钙钛矿电池；\n2）供应链安全方面关注风电轴承、高端数控机床、工业机器人零部件、国产软件；\n3）数字经济方面关注车路协同、元宇宙；\n4）传承创新发展方面关注中药配方颗粒。\n对于股票市场流动性，张夏团队认为2023年股市资金供需转净流入，流动性边际改善。资金供给端，明年随着市场企稳公募基金发行有望回暖不过老基金赎回压力或相应增大；美债收益率和美元指数双降将引导外资回流；个人养老金落地带来一定增量。资金需求端，IPO与再融资稳中有升，而解禁规模下降有助于缓解减持压力。综合供需测算，2023年A股资金或净流入700多亿元。\n\n在行业景气趋势方面，张夏团队预计景气度改善的5大领域：医药、信息技术部分、高端装备、地产及地产消费、疫后修复板块。预计未来景气度改善空间较大的5个细分行业依次是软件开发、医疗器械、化学制药、自动化装备、传媒。\n张夏团队也提到2023年A股面临的一些风险，包括疫情控制不及预期，经济陷入深度衰退；全球货币紧缩超预期，美国对华的超预期打压和遏制等等。\n",
        "Recommendation_links": [
            "https://new.qq.com/rain/a/20221201A01LCI00",
            null,
            "https://new.qq.com/rain/a/20221201A02PAR00",
            "https://new.qq.com/rain/a/20221130A0A93T00",
            "https://new.qq.com/rain/a/UTR2022112800023400",
            "https://new.qq.com/rain/a/UTR2022090700067800",
            "https://new.qq.com/rain/a/UTR2022090700068100",
            null,
            "https://new.qq.com/rain/a/20221201A03WOQ00",
            "https://new.qq.com/rain/a/20221201V028KM00",
            "https://new.qq.com/rain/a/20221201A01MZN00",
            "https://new.qq.com/rain/a/20221201A03GQJ00",
            "https://new.qq.com/rain/a/20221201A02SB200",
            null,
            "https://new.qq.com/rain/a/20221201A03HB800",
            "https://new.qq.com/rain/a/20221201A03ZOW00",
            "https://new.qq.com/rain/a/20221201A002UC00",
            "https://new.qq.com/rain/a/20221201A0046L00",
            "https://new.qq.com/rain/a/UTR2022090700070900",
            null,
            "https://new.qq.com/rain/a/20221201A003Z100",
            "https://new.qq.com/rain/a/20221201A00BNH00",
            "https://new.qq.com/rain/a/20221201A00IR400",
            "https://new.qq.com/rain/a/20221130A0AEM300",
            "https://new.qq.com/rain/a/20221130A07LVS00",
            "https://new.qq.com/rain/a/20221130A06WTL00",
            "https://new.qq.com/rain/a/20221201A0056R00",
            "https://new.qq.com/rain/a/20221201A0030300",
            "https://new.qq.com/rain/a/20221201A001HI00",
            null,
            "https://new.qq.com/rain/a/20221201A00E6700",
            "https://new.qq.com/rain/a/20221201A00QEY00",
            "https://new.qq.com/rain/a/20221130A07L5500",
            "https://new.qq.com/rain/a/UTR2022113000035500",
            "https://new.qq.com/rain/a/20221201A00FXN00",
            "https://new.qq.com/rain/a/20221130A0A7I000",
            "https://new.qq.com/rain/a/20221130A0A03500",
            "https://new.qq.com/rain/a/20221130A0A1JV00",
            "https://new.qq.com/rain/a/20221130V09QFG00",
            "https://new.qq.com/rain/a/20221130A09F2E00",
            "https://new.qq.com/rain/a/20221129A06O3S00",
            "https://new.qq.com/rain/a/20221130A098LA00",
            "https://new.qq.com/rain/a/20221130A08T7K00",
            "https://new.qq.com/rain/a/20221130A08YY200",
            "https://new.qq.com/rain/a/20221130A08Z2D00",
            "https://new.qq.com/rain/a/20221130A03YGM00",
            "https://new.qq.com/rain/a/20221130A090IW00",
            "https://new.qq.com/rain/a/20221130A092MR00",
            null,
            "https://new.qq.com/rain/a/20221130A05QZU00",
            "https://new.qq.com/rain/a/20221130A04QCH00",
            "https://new.qq.com/rain/a/20221130A08HZN00",
            "https://new.qq.com/rain/a/20221130A0872B00",
            "https://new.qq.com/rain/a/20221130A05BQX00",
            "https://new.qq.com/rain/a/20221130A0876800",
            "https://new.qq.com/rain/a/20221130A0735500",
            "https://new.qq.com/rain/a/20221130A0795N00",
            "https://new.qq.com/rain/a/20221130A07LY200",
            "https://new.qq.com/rain/a/20221130A07LJ400",
            "https://new.qq.com/rain/a/20221130A07XFG00",
            "https://new.qq.com/rain/a/20221130A07XLE00",
            "https://new.qq.com/rain/a/20221130A080FT00",
            "https://new.qq.com/rain/a/20221130A0808900",
            "https://new.qq.com/rain/a/20221130A080BP00",
            "https://new.qq.com/rain/a/20221130A07Z7E00",
            "https://new.qq.com/rain/a/20221130A07LUM00",
            "https://new.qq.com/rain/a/20221130A06WEU00",
            null,
            "https://new.qq.com/rain/a/20221130A076C300",
            "https://new.qq.com/rain/a/20221130A06X9P00",
            "https://new.qq.com/rain/a/20221130A06IMV00",
            "https://new.qq.com/rain/a/20221130A05Y4I00",
            "https://new.qq.com/rain/a/20221130A06Q1F00",
            "https://new.qq.com/rain/a/20221130A05UCR00",
            "https://new.qq.com/rain/a/20221130A068NV00",
            "https://new.qq.com/rain/a/20221130V02Z4S00",
            "https://new.qq.com/rain/a/20221130A0411R00",
            null,
            "https://new.qq.com/rain/a/20221130A05SGP00",
            "https://new.qq.com/rain/a/20221130A01QQQ00",
            "https://new.qq.com/rain/a/UTR2022112000014600",
            "https://new.qq.com/rain/a/20221130A04IP400",
            "https://new.qq.com/rain/a/20221130A05GZJ00",
            "https://new.qq.com/rain/a/20221130A050XV00",
            "https://new.qq.com/rain/a/20221130A0529V00",
            "https://new.qq.com/rain/a/20221130A03BQR00",
            "https://new.qq.com/rain/a/20221129V02NWN00",
            "https://new.qq.com/rain/a/20221130A044X800",
            "https://new.qq.com/rain/a/20221130A041CD00",
            "https://new.qq.com/rain/a/UTR2022110100035500",
            "https://new.qq.com/rain/a/20221130A031F400",
            "https://new.qq.com/rain/a/20221129A085D800",
            "https://new.qq.com/rain/a/20221130A0256J00",
            "https://new.qq.com/rain/a/20221130A01OOS00",
            "https://new.qq.com/rain/a/20221129A0AA9J00",
            "https://new.qq.com/rain/a/20221130A026K100",
            "https://new.qq.com/rain/a/20221130A0280600",
            "https://new.qq.com/rain/a/20221130A023RT00",
            "https://new.qq.com/rain/a/20221130V0252V00",
            "https://new.qq.com/rain/a/20221130A01NLE00",
            "https://new.qq.com/rain/a/20221130A00X2000",
            "https://new.qq.com/rain/a/20221129A0766Y00",
            "https://new.qq.com/rain/a/20221129A0AFDS00",
            "https://new.qq.com/rain/a/20221130A0130J00",
            "https://new.qq.com/rain/a/20221130A00S8Z00",
            "https://new.qq.com/rain/a/20221129A09Y3Z00",
            "https://new.qq.com/rain/a/20221129A0A2OS00",
            "https://new.qq.com/rain/a/20221129A09OIJ00",
            "https://new.qq.com/rain/a/20221129A09X7V00",
            "https://new.qq.com/rain/a/20221130A004HB00",
            "https://new.qq.com/rain/a/20221129A099OE00",
            "https://new.qq.com/rain/a/20221129A0881Q00",
            "https://new.qq.com/rain/a/20221129A09UD600",
            "https://new.qq.com/rain/a/20221129V05ZLY00",
            "https://new.qq.com/rain/a/20221129A0A4Z400",
            "https://new.qq.com/rain/a/20221129A08BJE00",
            "https://new.qq.com/rain/a/20221129A0A0E500",
            "https://new.qq.com/rain/a/20221129A0AFJ500",
            "https://new.qq.com/rain/a/20221129A044TH00",
            "https://new.qq.com/rain/a/20221129A09K8I00",
            "https://new.qq.com/rain/a/20221129A09JL000",
            "https://new.qq.com/rain/a/20221129A09MKT00",
            "https://new.qq.com/rain/a/20221129A09I5C00",
            "https://new.qq.com/rain/a/20221129A05NKS00",
            "https://new.qq.com/rain/a/20221129A09KC800",
            "https://new.qq.com/rain/a/20221129A09DX300",
            "https://new.qq.com/rain/a/20221129A09E6X00",
            "https://new.qq.com/rain/a/20221129A09ECX00",
            "https://new.qq.com/rain/a/20221129A08Y3600",
            "https://new.qq.com/rain/a/20221129A095S200",
            "https://new.qq.com/rain/a/20221129A090LU00",
            "https://new.qq.com/rain/a/20221129A07YYN00",
            "https://new.qq.com/rain/a/20221129A08E4300",
            "https://new.qq.com/rain/a/20221129A087LZ00",
            "https://new.qq.com/rain/a/20221129A0843700",
            "https://new.qq.com/rain/a/20221129A08BJ900",
            "https://new.qq.com/rain/a/20221129A07MXZ00",
            "https://new.qq.com/rain/a/20221129A03VGY00",
            "https://new.qq.com/rain/a/UTR2022112900029900",
            "https://new.qq.com/rain/a/20221129A0706L00",
            "https://new.qq.com/rain/a/20221129A06T9Q00",
            "https://new.qq.com/rain/a/20221129A06GI600",
            "https://new.qq.com/rain/a/20221129A036U800",
            "https://new.qq.com/rain/a/20221129V06FY500",
            "https://new.qq.com/rain/a/20221129A03Y5K00",
            "https://new.qq.com/rain/a/20221129V05XXY00",
            "https://new.qq.com/rain/a/20221129V06EY200",
            "https://new.qq.com/rain/a/20221129A06LRT00",
            "https://new.qq.com/rain/a/20221129A06DT100",
            "https://new.qq.com/rain/a/20221129A060NU00",
            "https://new.qq.com/rain/a/20221129A05L8000",
            "https://new.qq.com/rain/a/20221129V021AM00",
            "https://new.qq.com/rain/a/20221129A04BS100",
            "https://new.qq.com/rain/a/20221129A04WCP00",
            "https://new.qq.com/rain/a/20221129A04QXV00",
            "https://new.qq.com/rain/a/20221129A04Y4M00",
            "https://new.qq.com/rain/a/FIN2022112800046900",
            "https://new.qq.com/rain/a/20221129A041RR00",
            "https://new.qq.com/rain/a/20221129A00X4800",
            "https://new.qq.com/rain/a/20221129A02MF800",
            "https://new.qq.com/rain/a/20221129A00UYX00",
            "https://new.qq.com/rain/a/20221129A021TD00",
            "https://new.qq.com/rain/a/20221129A004QB00",
            "https://new.qq.com/rain/a/20221129A00WDA00",
            "https://new.qq.com/rain/a/20221129A01G3V00",
            "https://new.qq.com/rain/a/20221128V01D3900",
            "https://new.qq.com/rain/a/20221129A014HF00",
            "https://new.qq.com/rain/a/20221129A00ITV00",
            "https://new.qq.com/rain/a/20221129A00J1000",
            "https://new.qq.com/rain/a/20221128A0A4Q700",
            "https://new.qq.com/rain/a/20221129A00OOH00",
            "https://new.qq.com/rain/a/20221129A0048Y00",
            "https://new.qq.com/rain/a/20221128A08ERC00",
            "https://new.qq.com/rain/a/20221128A084PK00",
            "https://new.qq.com/rain/a/20221128A08SDK00",
            "https://new.qq.com/rain/a/20221129A00G4H00",
            "https://new.qq.com/rain/a/20221128A09V0300",
            "https://new.qq.com/rain/a/20221128A0A71300",
            "https://new.qq.com/rain/a/20221128A082AA00",
            "https://new.qq.com/rain/a/20221128A069ZV00",
            "https://new.qq.com/rain/a/20221128A082EX00",
            "https://new.qq.com/rain/a/20221128A09J1I00",
            "https://new.qq.com/rain/a/20221128A0A24400",
            "https://new.qq.com/rain/a/20221128A09WVD00",
            "https://new.qq.com/rain/a/20221128A087BZ00",
            "https://new.qq.com/rain/a/20221128A099GW00",
            "https://new.qq.com/rain/a/20221128A09GEJ00",
            "https://new.qq.com/rain/a/20221128A05ITC00",
            "https://new.qq.com/rain/a/20221128A07N3000",
            "https://new.qq.com/rain/a/20221128A08AFA00",
            "https://new.qq.com/rain/a/20221128A08B9T00",
            "https://new.qq.com/rain/a/20221128A08F0300",
            "https://new.qq.com/rain/a/20221128A08DL900",
            "https://new.qq.com/rain/a/20221128A08DZF00",
            "https://new.qq.com/rain/a/20221128A08GR500",
            "https://new.qq.com/rain/a/20221128A08N0E00",
            "https://new.qq.com/rain/a/20221128A08LQG00",
            "https://new.qq.com/rain/a/20221128A08NQ500",
            "https://new.qq.com/rain/a/20221128A08OPM00",
            "https://new.qq.com/rain/a/20221128A08QQM00",
            "https://new.qq.com/rain/a/20221128A08QY300",
            "https://new.qq.com/rain/a/20221128A08DBU00",
            "https://new.qq.com/rain/a/20221128A07OMG00",
            "https://new.qq.com/rain/a/20221128A01H4I00",
            "https://new.qq.com/rain/a/20221128A07N2Z00",
            "https://new.qq.com/rain/a/20221128A02V0300",
            "https://new.qq.com/rain/a/20221128A05PBS00"
        ]
    }
}