{
    "195": {
        "Tag": "security",
        "Id": "20221122A06FQ0_199",
        "Url": "https://new.qq.com/rain/a/20221122A06FQ000",
        "Title": "就是这么壕！马斯克年内身家缩水千亿 仍能稳坐全球首富",
        "Author": NaN,
        "Publish_Date": "2022-11-22",
        "Post_time": "17:13",
        "Content": "财联社11月22日讯（编辑 赵昊）截至周一（11月21日）美股收盘，电动汽车龙头特斯拉股价大跌近7%，报每股167.87美元，年内跌幅达到了52%，这也让公司CEO埃隆·马斯克的身家缩水了超千亿美元。\n根据媒体汇编的亿万富翁指数，马斯克的净资产在昨日一天内就蒸发了85.9亿美元，年内缩水总额达到了1,010亿美元，幅度达到了37.2%。\n\n但即使如此，马斯克依然以1,700亿美元的净资产稳坐全球首富榜榜首，领先第二名法国奢侈品巨头LVMH总裁兼CEO贝尔纳·阿尔诺近130亿美元。\n而在福布斯的亿万富翁榜单中，马斯克也以1,813亿美元位列榜首，但对奢侈品教父的领先不到59亿美元。\n\n特斯拉年内腰斩是身家缩水千亿主因\n马斯克的净资产中很大一部分是特斯拉股票，因此，他的身家与公司股价走势之间的关联度很高。目前特斯拉股价正位于2020年11月以来的低点，并且52%的年内跌幅也显著高于纳斯达克100指数的29%。\n特斯拉股票的跌势是众多因素结合的后果。大环境上，美国从新冠大流行初期的大肆签发纾困支票，转变到如今美联储步伐极快的加息周期，金融条件可以说的上是发生了翻天覆地的变化。\n需要指出的是，特斯拉不仅是电动汽车股，也是一支科技股，与其他科技巨头一样，公司的成长属性对利率非常敏感，也因此成为年内被集中抛售的对象。\n公司业务方面，特斯拉自疫情爆发以来一直面临着供应链瓶颈以及原材料价格飙升的问题，而今年俄乌冲突的升级更是加剧了这两项因素的负面作用。除此以外，汽车因缺陷被勒令召回、自动驾驶技术的难产也是困扰业务的几大原因。\n另外，马斯克经营的公司数量过多也是风险之一。此前他以440亿美元的总价收购了社交平台推特并将其私有化，让投资者担心经营推特等其他公司可能会分散他对电动汽车的专注度。\n",
        "Recommendation_links": [
            "https://new.qq.com/rain/a/20221201A01LCI00",
            null,
            "https://new.qq.com/rain/a/20221201A02PAR00",
            "https://new.qq.com/rain/a/20221201A04H4I00",
            "https://new.qq.com/rain/a/UTR2022112800023400",
            "https://new.qq.com/rain/a/UTR2022090700067800",
            "https://new.qq.com/rain/a/UTR2022090700068100",
            "https://new.qq.com/rain/a/20221201A03WOQ00",
            "https://new.qq.com/rain/a/20221201V028KM00",
            "https://new.qq.com/rain/a/20221201A01MZN00",
            "https://new.qq.com/rain/a/20221201A03GQJ00",
            "https://new.qq.com/rain/a/20221201A02SB200",
            "https://new.qq.com/rain/a/20221201A03HB800",
            "https://new.qq.com/rain/a/20221201A03ZOW00",
            "https://new.qq.com/rain/a/20221201A002UC00",
            "https://new.qq.com/rain/a/20221201A0046L00",
            "https://new.qq.com/rain/a/UTR2022090700070900",
            "https://new.qq.com/rain/a/20221201A003Z100",
            "https://new.qq.com/rain/a/20221130A0A93T00",
            "https://new.qq.com/rain/a/20221201A00BNH00",
            "https://new.qq.com/rain/a/20221201A00IR400",
            "https://new.qq.com/rain/a/20221130A0AEM300",
            "https://new.qq.com/rain/a/20221130A07LVS00",
            "https://new.qq.com/rain/a/20221130A06WTL00",
            "https://new.qq.com/rain/a/20221201A0056R00",
            "https://new.qq.com/rain/a/20221201A0030300",
            null,
            "https://new.qq.com/rain/a/20221201A001HI00",
            "https://new.qq.com/rain/a/20221201A00E6700",
            "https://new.qq.com/rain/a/20221201A00QEY00",
            "https://new.qq.com/rain/a/20221130A07L5500",
            "https://new.qq.com/rain/a/UTR2022113000035500",
            "https://new.qq.com/rain/a/20221201A00FXN00",
            "https://new.qq.com/rain/a/20221130A0A7I000",
            "https://new.qq.com/rain/a/20221130A0A03500",
            "https://new.qq.com/rain/a/20221130A0A1JV00",
            "https://new.qq.com/rain/a/20221130V09QFG00",
            "https://new.qq.com/rain/a/20221130A09F2E00",
            "https://new.qq.com/rain/a/20221129A06O3S00",
            "https://new.qq.com/rain/a/20221130A098LA00",
            "https://new.qq.com/rain/a/20221130A08T7K00",
            "https://new.qq.com/rain/a/20221130A08YY200",
            "https://new.qq.com/rain/a/20221130A08Z2D00",
            "https://new.qq.com/rain/a/20221130A03YGM00",
            "https://new.qq.com/rain/a/20221130A090IW00",
            null,
            "https://new.qq.com/rain/a/20221130A092MR00",
            "https://new.qq.com/rain/a/20221130A05QZU00",
            "https://new.qq.com/rain/a/20221130A04QCH00",
            "https://new.qq.com/rain/a/20221130A08HZN00",
            "https://new.qq.com/rain/a/20221130A0872B00",
            "https://new.qq.com/rain/a/20221130A05BQX00",
            "https://new.qq.com/rain/a/20221130A0876800",
            "https://new.qq.com/rain/a/20221130A0735500",
            "https://new.qq.com/rain/a/20221130A0795N00",
            "https://new.qq.com/rain/a/20221130A07LY200",
            "https://new.qq.com/rain/a/20221130A07LJ400",
            "https://new.qq.com/rain/a/20221130A07XFG00",
            "https://new.qq.com/rain/a/20221130A07XLE00",
            "https://new.qq.com/rain/a/20221130A080FT00",
            "https://new.qq.com/rain/a/20221130A0808900",
            "https://new.qq.com/rain/a/20221130A080BP00",
            "https://new.qq.com/rain/a/20221130A07Z7E00",
            "https://new.qq.com/rain/a/20221130A07LUM00",
            null,
            "https://new.qq.com/rain/a/20221130A06WEU00",
            "https://new.qq.com/rain/a/20221130A076C300",
            "https://new.qq.com/rain/a/20221130A06X9P00",
            "https://new.qq.com/rain/a/20221130A06IMV00",
            "https://new.qq.com/rain/a/20221130A05Y4I00",
            "https://new.qq.com/rain/a/20221130A06Q1F00",
            "https://new.qq.com/rain/a/20221130A05UCR00",
            "https://new.qq.com/rain/a/20221130A068NV00",
            "https://new.qq.com/rain/a/20221130V02Z4S00",
            null,
            "https://new.qq.com/rain/a/20221130A0411R00",
            "https://new.qq.com/rain/a/20221130A05SGP00",
            "https://new.qq.com/rain/a/20221130A01QQQ00",
            "https://new.qq.com/rain/a/UTR2022112000014600",
            "https://new.qq.com/rain/a/20221130A04IP400",
            "https://new.qq.com/rain/a/20221130A05GZJ00",
            "https://new.qq.com/rain/a/20221130A050XV00",
            "https://new.qq.com/rain/a/20221130A0529V00",
            "https://new.qq.com/rain/a/20221130A03BQR00",
            null,
            "https://new.qq.com/rain/a/20221129V02NWN00",
            "https://new.qq.com/rain/a/20221130A044X800",
            "https://new.qq.com/rain/a/20221130A041CD00",
            "https://new.qq.com/rain/a/UTR2022110100035500",
            "https://new.qq.com/rain/a/20221130A031F400",
            "https://new.qq.com/rain/a/20221129A085D800",
            "https://new.qq.com/rain/a/20221130A0256J00",
            "https://new.qq.com/rain/a/20221130A01OOS00",
            "https://new.qq.com/rain/a/20221129A0AA9J00",
            "https://new.qq.com/rain/a/20221130A026K100",
            "https://new.qq.com/rain/a/20221130A0280600",
            "https://new.qq.com/rain/a/20221130A023RT00",
            "https://new.qq.com/rain/a/20221130V0252V00",
            "https://new.qq.com/rain/a/20221130A01NLE00",
            "https://new.qq.com/rain/a/20221130A00X2000",
            "https://new.qq.com/rain/a/20221129A0766Y00",
            "https://new.qq.com/rain/a/20221129A0AFDS00",
            "https://new.qq.com/rain/a/20221130A0130J00",
            "https://new.qq.com/rain/a/20221130A00S8Z00",
            "https://new.qq.com/rain/a/20221129A09Y3Z00",
            "https://new.qq.com/rain/a/20221129A0A2OS00",
            "https://new.qq.com/rain/a/20221129A09OIJ00",
            "https://new.qq.com/rain/a/20221129A09X7V00",
            "https://new.qq.com/rain/a/20221130A004HB00",
            "https://new.qq.com/rain/a/20221129A099OE00",
            "https://new.qq.com/rain/a/20221129A0881Q00",
            "https://new.qq.com/rain/a/20221129A09UD600",
            "https://new.qq.com/rain/a/20221129V05ZLY00",
            "https://new.qq.com/rain/a/20221129A0A4Z400",
            "https://new.qq.com/rain/a/20221129A08BJE00",
            "https://new.qq.com/rain/a/20221129A0A0E500",
            "https://new.qq.com/rain/a/20221129A0AFJ500",
            "https://new.qq.com/rain/a/20221129A044TH00",
            "https://new.qq.com/rain/a/20221129A09K8I00",
            "https://new.qq.com/rain/a/20221129A09JL000",
            "https://new.qq.com/rain/a/20221129A09MKT00",
            "https://new.qq.com/rain/a/20221129A09I5C00",
            "https://new.qq.com/rain/a/20221129A05NKS00",
            "https://new.qq.com/rain/a/20221129A09KC800",
            "https://new.qq.com/rain/a/20221129A09DX300",
            "https://new.qq.com/rain/a/20221129A09E6X00",
            "https://new.qq.com/rain/a/20221129A09ECX00",
            "https://new.qq.com/rain/a/20221129A08Y3600",
            "https://new.qq.com/rain/a/20221129A095S200",
            "https://new.qq.com/rain/a/20221129A090LU00",
            "https://new.qq.com/rain/a/20221129A07YYN00",
            "https://new.qq.com/rain/a/20221129A08E4300",
            "https://new.qq.com/rain/a/20221129A087LZ00",
            "https://new.qq.com/rain/a/20221129A0843700",
            "https://new.qq.com/rain/a/20221129A08BJ900",
            "https://new.qq.com/rain/a/20221129A07MXZ00",
            "https://new.qq.com/rain/a/20221129A03VGY00",
            "https://new.qq.com/rain/a/UTR2022112900029900",
            "https://new.qq.com/rain/a/20221129A0706L00",
            "https://new.qq.com/rain/a/20221129A06T9Q00",
            "https://new.qq.com/rain/a/20221129A06GI600",
            "https://new.qq.com/rain/a/20221129A036U800",
            "https://new.qq.com/rain/a/20221129V06FY500",
            "https://new.qq.com/rain/a/20221129A03Y5K00",
            "https://new.qq.com/rain/a/20221129V05XXY00",
            "https://new.qq.com/rain/a/20221129V06EY200",
            "https://new.qq.com/rain/a/20221129A06LRT00",
            "https://new.qq.com/rain/a/20221129A06DT100",
            "https://new.qq.com/rain/a/20221129A060NU00",
            "https://new.qq.com/rain/a/20221129A05L8000",
            "https://new.qq.com/rain/a/20221129V021AM00",
            "https://new.qq.com/rain/a/20221129A04BS100",
            "https://new.qq.com/rain/a/20221129A04WCP00",
            "https://new.qq.com/rain/a/20221129A04QXV00",
            "https://new.qq.com/rain/a/20221129A04Y4M00",
            "https://new.qq.com/rain/a/FIN2022112800046900",
            "https://new.qq.com/rain/a/20221129A041RR00",
            "https://new.qq.com/rain/a/20221129A00X4800",
            "https://new.qq.com/rain/a/20221129A02MF800",
            "https://new.qq.com/rain/a/20221129A00UYX00",
            "https://new.qq.com/rain/a/20221129A021TD00",
            "https://new.qq.com/rain/a/20221129A004QB00",
            "https://new.qq.com/rain/a/20221129A00WDA00",
            "https://new.qq.com/rain/a/20221129A01G3V00",
            "https://new.qq.com/rain/a/20221128V01D3900",
            "https://new.qq.com/rain/a/20221129A014HF00",
            "https://new.qq.com/rain/a/20221129A00ITV00",
            "https://new.qq.com/rain/a/20221129A00J1000",
            "https://new.qq.com/rain/a/20221128A0A4Q700",
            "https://new.qq.com/rain/a/20221129A00OOH00",
            "https://new.qq.com/rain/a/20221129A0048Y00",
            "https://new.qq.com/rain/a/20221128A08ERC00",
            "https://new.qq.com/rain/a/20221128A084PK00",
            "https://new.qq.com/rain/a/20221128A08SDK00",
            "https://new.qq.com/rain/a/20221129A00G4H00",
            "https://new.qq.com/rain/a/20221128A09V0300",
            "https://new.qq.com/rain/a/20221128A0A71300",
            "https://new.qq.com/rain/a/20221128A082AA00",
            "https://new.qq.com/rain/a/20221128A069ZV00",
            "https://new.qq.com/rain/a/20221128A082EX00",
            "https://new.qq.com/rain/a/20221128A09J1I00",
            "https://new.qq.com/rain/a/20221128A0A24400",
            "https://new.qq.com/rain/a/20221128A09WVD00",
            "https://new.qq.com/rain/a/20221128A087BZ00",
            "https://new.qq.com/rain/a/20221128A099GW00",
            "https://new.qq.com/rain/a/20221128A09GEJ00",
            "https://new.qq.com/rain/a/20221128A05ITC00",
            "https://new.qq.com/rain/a/20221128A07N3000",
            "https://new.qq.com/rain/a/20221128A08AFA00",
            "https://new.qq.com/rain/a/20221128A08B9T00",
            "https://new.qq.com/rain/a/20221128A08F0300",
            "https://new.qq.com/rain/a/20221128A08DL900",
            "https://new.qq.com/rain/a/20221128A08DZF00",
            "https://new.qq.com/rain/a/20221128A08GR500",
            "https://new.qq.com/rain/a/20221128A08N0E00",
            "https://new.qq.com/rain/a/20221128A08LQG00",
            "https://new.qq.com/rain/a/20221128A08NQ500",
            "https://new.qq.com/rain/a/20221128A08OPM00",
            "https://new.qq.com/rain/a/20221128A08QQM00",
            "https://new.qq.com/rain/a/20221128A08QY300",
            "https://new.qq.com/rain/a/20221128A08DBU00",
            "https://new.qq.com/rain/a/20221128A07OMG00",
            "https://new.qq.com/rain/a/20221128A01H4I00",
            "https://new.qq.com/rain/a/20221128A07N2Z00",
            "https://new.qq.com/rain/a/20221128A02V0300"
        ]
    }
}