{
    "200": {
        "Tag": "car",
        "Id": "20221128A00O3I00_247",
        "Url": "https://new.qq.com/omn/20221128/20221128A00O3I00.html",
        "Title": "现代伊兰特10月销量下滑10％ 悦动降40％ 胜达暴跌44％",
        "Author": "网上车市",
        "Publish_Date": "2022-11-28",
        "Post_time": "07:13",
        "Content": "新车交强险购买数显示，今年10月，北京现代第七代伊兰特上险量为9,704辆，同比降低9.88%。紧凑型家轿悦动同期上险量为1,384辆，同比降低39.88%；中型SUV第四代胜达上险量仅321辆，同比降43.59%。\n6月1日，北京现代推出了新车购置税100%全免、至高1.5万元油费补贴、至高1万元置换补贴、终身免费基础保养及质保等一系列利好政策，但从购买情况看未起到明显效果。\n\n\n\n其他车型方面，ix35和途胜L是北京现代为数不多的亮点，前者10月上险量为6,180辆，同比增长16.60%，环比下降8.42%；后者10月上险量为4,041辆，同比增长134.81%，环比下降1.99%。\n在轿车版块中，第十代索纳塔10月上险量仅为574辆，同比下降10.03%，在与大众迈腾/帕萨特、本田雅阁、丰田凯美瑞等同级对手的竞争中毫无存在感。\n\n除了出台多重利好购车政策打“价格战”外，北京现代也加快了新品导入节奏，下半年接连推出了包括第四代胜达旅行家、全新菲斯塔N Line、第五代途胜L 8AT等改款车型。据规划，北京现代接下来还将推出新库斯途和第十代索纳塔中改款车型。\n",
        "Recommendation_links": NaN
    }
}